miracord/__init__.py
miracord/client.py
miracord_py-0.0.1.dist-info/METADATA
miracord_py-0.0.1.dist-info/WHEEL
miracord_py-0.0.1.dist-info/top_level.txt
miracord_py-0.0.1.dist-info/RECORD
