Metadata-Version: 2.4
Name: miracord-py
Version: 0.0.1
Summary: Ultra High Performance, Stackless Discord Library for Python
Home-page: https://github.com/seninkullaniciadın/miracord-py
Author: Miracord Dev
Classifier: Programming Language :: Python :: 3
Classifier: License :: OSI Approved :: MIT License
Classifier: Operating System :: OS Independent
Requires-Python: >=3.8
Requires-Dist: aiohttp>=3.8.0
Requires-Dist: websockets>=10.0
Dynamic: author
Dynamic: classifier
Dynamic: description
Dynamic: description-content-type
Dynamic: home-page
Dynamic: requires-dist
Dynamic: requires-python
Dynamic: summary
